gatekeep/__init__.py
gatekeep/errors.py
gatekeep/log.py
gatekeep/settings.py
gatekeep/users.py
gatekeep-0.1.2.dist-info/WHEEL
gatekeep-0.1.2.dist-info/METADATA
gatekeep-0.1.2.dist-info/RECORD
